src/nebari_plugin_airflow/__about__.py
src/nebari_plugin_airflow/__init__.py
src/nebari_plugin_airflow/plugin.py
src/nebari_plugin_airflow/template/main.tf
src/nebari_plugin_airflow/template/outputs.tf
src/nebari_plugin_airflow/template/variables.tf
src/nebari_plugin_airflow/template/versions.tf
src/nebari_plugin_airflow/template/chart/Chart.yaml
src/nebari_plugin_airflow/template/chart/values.yaml
src/nebari_plugin_airflow/template/chart/files/webserver_config.py
src/nebari_plugin_airflow/template/chart/templates/ingress.yaml
src/nebari_plugin_airflow/template/chart/templates/secrets.yaml
nebari_plugin_airflow-0.0.2.dist-info/METADATA
nebari_plugin_airflow-0.0.2.dist-info/WHEEL
nebari_plugin_airflow-0.0.2.dist-info/entry_points.txt
nebari_plugin_airflow-0.0.2.dist-info/licenses/LICENSE
nebari_plugin_airflow-0.0.2.dist-info/RECORD
